{
  "meta": {
    "last_updated": "2026-04-13T23:29:46Z",
    "portfolio_bias": "RISK ON",
    "portfolio_score": 84,
    "interpretation": "Risk-on environment \u2014 run full playbook with normal sizing"
  },
  "assets": [
    {
      "ticker": "SPX",
      "yf_ticker": "^GSPC",
      "close": 6886.24,
      "as_of": "Apr 13, 2026 close",
      "composite_score": 89,
      "bias": "FULL BULL",
      "alignment": 3,
      "vix": 19.12,
      "sma": {
        "sma10": {
          "value": 6656.95,
          "above": true,
          "distance_pct": 3.44,
          "days_count": 9
        },
        "sma20": {
          "value": 6614.9,
          "above": true,
          "distance_pct": 4.1,
          "days_count": 6
        },
        "sma50": {
          "value": 6760.32,
          "above": true,
          "distance_pct": 1.86,
          "days_count": 4
        },
        "sma200": {
          "value": 6666.59,
          "above": true,
          "distance_pct": 3.29,
          "days_count": 4
        }
      }
    },
    {
      "ticker": "QQQ",
      "yf_ticker": "QQQ",
      "close": 617.39,
      "as_of": "Apr 13, 2026 close",
      "composite_score": 89,
      "bias": "FULL BULL",
      "alignment": 3,
      "vix": 19.12,
      "sma": {
        "sma10": {
          "value": 592.66,
          "above": true,
          "distance_pct": 4.17,
          "days_count": 8
        },
        "sma20": {
          "value": 589.63,
          "above": true,
          "distance_pct": 4.71,
          "days_count": 6
        },
        "sma50": {
          "value": 599.87,
          "above": true,
          "distance_pct": 2.92,
          "days_count": 4
        },
        "sma200": {
          "value": 595.71,
          "above": true,
          "distance_pct": 3.64,
          "days_count": 4
        }
      }
    },
    {
      "ticker": "IWM",
      "yf_ticker": "IWM",
      "close": 265.07,
      "as_of": "Apr 13, 2026 close",
      "composite_score": 89,
      "bias": "FULL BULL",
      "alignment": 3,
      "vix": 19.12,
      "sma": {
        "sma10": {
          "value": 254.25,
          "above": true,
          "distance_pct": 4.25,
          "days_count": 9
        },
        "sma20": {
          "value": 250.78,
          "above": true,
          "distance_pct": 5.7,
          "days_count": 8
        },
        "sma50": {
          "value": 256.13,
          "above": true,
          "distance_pct": 3.49,
          "days_count": 4
        },
        "sma200": {
          "value": 243.24,
          "above": true,
          "distance_pct": 8.98,
          "days_count": 9
        }
      }
    },
    {
      "ticker": "BTC",
      "yf_ticker": "BTC-USD",
      "close": 74661.78,
      "as_of": "Apr 13, 2026",
      "composite_score": 63,
      "bias": "MIXED",
      "alignment": 3,
      "vix": null,
      "sma": {
        "sma10": {
          "value": 71141.26,
          "above": true,
          "distance_pct": 4.95,
          "days_count": 10
        },
        "sma20": {
          "value": 69347.51,
          "above": true,
          "distance_pct": 7.66,
          "days_count": 9
        },
        "sma50": {
          "value": 69282.62,
          "above": true,
          "distance_pct": 7.76,
          "days_count": 9
        },
        "sma200": {
          "value": 87700.3,
          "above": false,
          "distance_pct": -14.87,
          "days_count": 162
        }
      }
    }
  ]
}