{
  "meta": {
    "last_updated": "2026-05-18T16:22:10Z",
    "portfolio_bias": "RISK ON",
    "portfolio_score": 71,
    "interpretation": "Risk-on environment \u2014 run full playbook with normal sizing"
  },
  "assets": [
    {
      "ticker": "SPX",
      "yf_ticker": "^GSPC",
      "close": 7394.88,
      "as_of": "May 18, 2026 close",
      "composite_score": 95,
      "bias": "FULL BULL",
      "alignment": 4,
      "vix": 18.64,
      "sma": {
        "sma10": {
          "value": 7392.31,
          "above": true,
          "distance_pct": 0.03,
          "days_count": 34
        },
        "sma20": {
          "value": 7274.35,
          "above": true,
          "distance_pct": 1.66,
          "days_count": 31
        },
        "sma50": {
          "value": 6934.2,
          "above": true,
          "distance_pct": 6.64,
          "days_count": 29
        },
        "sma200": {
          "value": 6785.15,
          "above": true,
          "distance_pct": 8.99,
          "days_count": 29
        }
      }
    },
    {
      "ticker": "QQQ",
      "yf_ticker": "QQQ",
      "close": 704.73,
      "as_of": "May 18, 2026 close",
      "composite_score": 75,
      "bias": "RISK ON",
      "alignment": 3,
      "vix": 18.64,
      "sma": {
        "sma10": {
          "value": 705.22,
          "above": false,
          "distance_pct": -0.07,
          "days_count": 1
        },
        "sma20": {
          "value": 683.26,
          "above": true,
          "distance_pct": 3.14,
          "days_count": 31
        },
        "sma50": {
          "value": 633.41,
          "above": true,
          "distance_pct": 11.26,
          "days_count": 29
        },
        "sma200": {
          "value": 610.54,
          "above": true,
          "distance_pct": 15.43,
          "days_count": 29
        }
      }
    },
    {
      "ticker": "IWM",
      "yf_ticker": "IWM",
      "close": 276.59,
      "as_of": "May 18, 2026 close",
      "composite_score": 61,
      "bias": "MIXED",
      "alignment": 3,
      "vix": 18.64,
      "sma": {
        "sma10": {
          "value": 282.5,
          "above": false,
          "distance_pct": -2.09,
          "days_count": 2
        },
        "sma20": {
          "value": 279.32,
          "above": false,
          "distance_pct": -0.98,
          "days_count": 2
        },
        "sma50": {
          "value": 264.29,
          "above": true,
          "distance_pct": 4.65,
          "days_count": 29
        },
        "sma200": {
          "value": 250.51,
          "above": true,
          "distance_pct": 10.41,
          "days_count": 34
        }
      }
    },
    {
      "ticker": "BTC",
      "yf_ticker": "BTC-USD",
      "close": 76538.42,
      "as_of": "May 18, 2026",
      "composite_score": 33,
      "bias": "RISK OFF",
      "alignment": 2,
      "vix": null,
      "sma": {
        "sma10": {
          "value": 79650.23,
          "above": false,
          "distance_pct": -3.91,
          "days_count": 4
        },
        "sma20": {
          "value": 79316.83,
          "above": false,
          "distance_pct": -3.5,
          "days_count": 4
        },
        "sma50": {
          "value": 75627.66,
          "above": true,
          "distance_pct": 1.2,
          "days_count": 44
        },
        "sma200": {
          "value": 81430.7,
          "above": false,
          "distance_pct": -6.01,
          "days_count": 197
        }
      }
    }
  ]
}