{
  "meta": {
    "last_updated": "2026-04-09T17:47:08Z",
    "portfolio_bias": "RISK ON",
    "portfolio_score": 78,
    "interpretation": "Risk-on environment \u2014 run full playbook with normal sizing"
  },
  "assets": [
    {
      "ticker": "SPX",
      "yf_ticker": "^GSPC",
      "close": 6831.1,
      "as_of": "Apr 9, 2026 close",
      "composite_score": 82,
      "bias": "RISK ON",
      "alignment": 2,
      "vix": 19.91,
      "sma": {
        "sma10": {
          "value": 6571.89,
          "above": true,
          "distance_pct": 3.94,
          "days_count": 7
        },
        "sma20": {
          "value": 6595.3,
          "above": true,
          "distance_pct": 3.58,
          "days_count": 4
        },
        "sma50": {
          "value": 6765.32,
          "above": true,
          "distance_pct": 0.97,
          "days_count": 2
        },
        "sma200": {
          "value": 6659.03,
          "above": true,
          "distance_pct": 2.58,
          "days_count": 2
        }
      }
    },
    {
      "ticker": "QQQ",
      "yf_ticker": "QQQ",
      "close": 609.65,
      "as_of": "Apr 9, 2026 close",
      "composite_score": 82,
      "bias": "RISK ON",
      "alignment": 2,
      "vix": 19.91,
      "sma": {
        "sma10": {
          "value": 583.39,
          "above": true,
          "distance_pct": 4.5,
          "days_count": 6
        },
        "sma20": {
          "value": 587.66,
          "above": true,
          "distance_pct": 3.74,
          "days_count": 4
        },
        "sma50": {
          "value": 600.51,
          "above": true,
          "distance_pct": 1.52,
          "days_count": 2
        },
        "sma200": {
          "value": 594.95,
          "above": true,
          "distance_pct": 2.47,
          "days_count": 2
        }
      }
    },
    {
      "ticker": "IWM",
      "yf_ticker": "IWM",
      "close": 262.79,
      "as_of": "Apr 9, 2026 close",
      "composite_score": 89,
      "bias": "FULL BULL",
      "alignment": 3,
      "vix": 19.91,
      "sma": {
        "sma10": {
          "value": 250.75,
          "above": true,
          "distance_pct": 4.8,
          "days_count": 7
        },
        "sma20": {
          "value": 249.16,
          "above": true,
          "distance_pct": 5.47,
          "days_count": 6
        },
        "sma50": {
          "value": 256.13,
          "above": true,
          "distance_pct": 2.6,
          "days_count": 2
        },
        "sma200": {
          "value": 242.73,
          "above": true,
          "distance_pct": 8.27,
          "days_count": 7
        }
      }
    },
    {
      "ticker": "BTC",
      "yf_ticker": "BTC-USD",
      "close": 72430.13,
      "as_of": "Apr 9, 2026",
      "composite_score": 55,
      "bias": "MIXED",
      "alignment": 2,
      "vix": null,
      "sma": {
        "sma10": {
          "value": 69075.8,
          "above": true,
          "distance_pct": 4.86,
          "days_count": 6
        },
        "sma20": {
          "value": 68707.67,
          "above": true,
          "distance_pct": 5.42,
          "days_count": 5
        },
        "sma50": {
          "value": 68879.42,
          "above": true,
          "distance_pct": 5.15,
          "days_count": 5
        },
        "sma200": {
          "value": 88482.07,
          "above": false,
          "distance_pct": -18.14,
          "days_count": 158
        }
      }
    }
  ]
}